random_timestamp/__init__.py
random_timestamp/__main__.py
random_timestamp-1.1.dist-info/LICENSE
random_timestamp-1.1.dist-info/METADATA
random_timestamp-1.1.dist-info/WHEEL
random_timestamp-1.1.dist-info/entry_points.txt
random_timestamp-1.1.dist-info/top_level.txt
random_timestamp-1.1.dist-info/RECORD
