Metadata-Version: 2.1
Name: random-timestamp
Version: 1.1
Summary: A Random Timestamp Generator
Home-page: https://github.com/HiroshiFuu/random_timestamp
Author: FENG Hao
Author-email: hiroshifuu@outlook.com
License: GPL v3.0
Download-URL: https://pypi.python.org/pypi/random-timestamp
Keywords: random date time timestamp
Platform: UNKNOWN
Classifier: Development Status :: 5 - Production/Stable
Classifier: License :: OSI Approved :: GNU General Public License v3 (GPLv3)
Classifier: Operating System :: OS Independent
Classifier: Programming Language :: Python :: 3
Classifier: Environment :: Console
Classifier: Natural Language :: English
Classifier: Intended Audience :: Developers
